hello_world_slava/__init__.py
hello_world_slava/main.py
hello_world_slava-1.0.2.dist-info/METADATA
hello_world_slava-1.0.2.dist-info/WHEEL
hello_world_slava-1.0.2.dist-info/top_level.txt
hello_world_slava-1.0.2.dist-info/RECORD
