Metadata-Version: 2.1
Name: hello-world-slava
Version: 1.0.2
Summary: Описание вашей библиотеки
Author: Ваше имя
Author-email: sv14.04@mail.ru
Classifier: Development Status :: 5 - Production/Stable
Classifier: Intended Audience :: Developers
Classifier: License :: OSI Approved :: MIT License
Classifier: Programming Language :: Python :: 3
Classifier: Programming Language :: Python :: 3.6
Classifier: Programming Language :: Python :: 3.7
Classifier: Programming Language :: Python :: 3.8
Classifier: Programming Language :: Python :: 3.9
